{
  "DataList": [
    {
      "GroupId": 32180,
      "SelectionGroup": 0,
      "BGMId": 76,
      "Sound": "",
      "Transition": 0,
      "BGName": 3932013926,
      "BGEffect": 0,
      "PopupFileName": "",
      "ScriptKr": "#title;제18화;그런 세계 2",
      "TextJp": "第18話;そんな世界も（２）",
      "TextTh": "ตอนที่ 18;โลกแบบนั้น (2)",
      "TextTw": "第18話;就算是這樣的世界（２）",
      "TextEn": "Episode 18;The Way of the World Part 2",
      "VoiceId": 0,
      "TeenMode": false
    },
    {
      "GroupId": 32180,
      "SelectionGroup": 0,
      "BGMId": 0,
      "Sound": "",
      "Transition": 0,
      "BGName": 0,
      "BGEffect": 0,
      "PopupFileName": "",
      "ScriptKr": "3;미카;09;시스터후드가…….\n#3;a",
      "TextJp": "シスターフッド……！？",
      "TextTh": "ชมรมซิสเตอร์...",
      "TextTw": "修女會……",
      "TextEn": "The Sisterhood...?",
      "VoiceId": 0,
      "TeenMode": false
    },
    {
      "GroupId": 32180,
      "SelectionGroup": 0,
      "BGMId": 0,
      "Sound": "",
      "Transition": 0,
      "BGName": 0,
      "BGEffect": 0,
      "PopupFileName": "",
      "ScriptKr": "3;미카;05;하나코, 네가……!\n#3;em;[!]",
      "TextJp": "っ、浦和ハナコ……！",
      "TextTh": "ฮานาโกะ... นี่เธอ...!",
      "TextTw": "花子，你竟然……！",
      "TextEn": "Urawa Hanako!",
      "VoiceId": 0,
      "TeenMode": false
    },
    {
      "GroupId": 32180,
      "SelectionGroup": 0,
      "BGMId": 0,
      "Sound": "",
      "Transition": 0,
      "BGName": 0,
      "BGEffect": 0,
      "PopupFileName": "",
      "ScriptKr": "1;하나코;06;……맞아요. 저도 계약을 하나 했을 뿐.\n#1;a\n#3;m5",
      "TextJp": "……まあ、ちょっとした約束をしましたので。",
      "TextTh": "ใช่ค่ะ... ฉันเองก็ทำสัญญาไว้เหมือนกัน",
      "TextTw": "……沒錯，我和他們訂下了約定。",
      "TextEn": "That's right. I did eventually decide to take someone up on their offer and made a pact of my own.",
      "VoiceId": 0,
      "TeenMode": false
    },
    {
      "GroupId": 32180,
      "SelectionGroup": 0,
      "BGMId": 0,
      "Sound": "",
      "Transition": 0,
      "BGName": 0,
      "BGEffect": 0,
      "PopupFileName": "",
      "ScriptKr": "3;미카;05;계약……?",
      "TextJp": "約束……？",
      "TextTh": "สัญญา...?",
      "TextTw": "約定……？",
      "TextEn": "A pact?",
      "VoiceId": 0,
      "TeenMode": false
    },
    {
      "GroupId": 32180,
      "SelectionGroup": 0,
      "BGMId": 0,
      "Sound": "",
      "Transition": 0,
      "BGName": 0,
      "BGEffect": 0,
      "PopupFileName": "",
      "ScriptKr": "1;하나코;06;당신이 알 필요는 없어요. 미카 씨. 그리고…….\n#1;em;[반응]",
      "TextJp": "あなたは知らなくても良いことですよ、ミカさん。",
      "TextTh": "คุณไม่จำเป็นต้องรู้หรอกค่ะ คุณมิกะ อีกอย่าง...",
      "TextTw": "你沒有必要知道，彌香同學。",
      "TextEn": "Nothing you need to concern yourself with. Besides...",
      "VoiceId": 0,
      "TeenMode": false
    },
    {
      "GroupId": 32180,
      "SelectionGroup": 0,
      "BGMId": 0,
      "Sound": "",
      "Transition": 0,
      "BGName": 1047754314,
      "BGEffect": 0,
      "PopupFileName": "",
      "ScriptKr": "#all;hide\n#st;[0,0];instant;1;",
      "TextJp": "",
      "TextTh": "",
      "TextTw": "",
      "TextEn": "",
      "VoiceId": 0,
      "TeenMode": false
    },
    {
      "GroupId": 32180,
      "SelectionGroup": 0,
      "BGMId": 0,
      "Sound": "",
      "Transition": 0,
      "BGName": 0,
      "BGEffect": 0,
      "PopupFileName": "",
      "ScriptKr": "#clearST",
      "TextJp": "",
      "TextTh": "",
      "TextTw": "",
      "TextEn": "",
      "VoiceId": 0,
      "TeenMode": false
    },
    {
      "GroupId": 32180,
      "SelectionGroup": 0,
      "BGMId": 0,
      "Sound": "SE_Boom_01",
      "Transition": 0,
      "BGName": 0,
      "BGEffect": 0,
      "PopupFileName": "",
      "ScriptKr": "#wait;1500",
      "TextJp": "",
      "TextTh": "",
      "TextTw": "",
      "TextEn": "",
      "VoiceId": 0,
      "TeenMode": false
    },
    {
      "GroupId": 32180,
      "SelectionGroup": 0,
      "BGMId": 0,
      "Sound": "",
      "Transition": 1122508889,
      "BGName": 3932013926,
      "BGEffect": 1377724294,
      "PopupFileName": "",
      "ScriptKr": "1;마리;01\n5;히나타;01\n#1;black\n#5;black",
      "TextJp": "",
      "TextTh": "",
      "TextTw": "",
      "TextEn": "",
      "VoiceId": 0,
      "TeenMode": false
    },
    {
      "GroupId": 32180,
      "SelectionGroup": 0,
      "BGMId": 0,
      "Sound": "",
      "Transition": 0,
      "BGName": 0,
      "BGEffect": 1377724294,
      "PopupFileName": "",
      "ScriptKr": "1;마리;09;오늘도 평화와 안녕이 그대와 함께하기를. ……콜록.\n#1;a\n#1;em;[속상함]\n#1;shake",
      "TextJp": "けほっ、今日も平和と安寧が、みなさんと共にありますように……けほっ。",
      "TextTh": "ขอให้ความสงบสุขและความรื่นรมย์จงอยู่กับคุณ... แค่กๆ ...",
      "TextTw": "希望今天平靜和安寧也和各位同在……咳咳。",
      "TextEn": "*cough* May peace and comfort find you today.",
      "VoiceId": 0,
      "TeenMode": false
    },
    {
      "GroupId": 32180,
      "SelectionGroup": 0,
      "BGMId": 0,
      "Sound": "",
      "Transition": 0,
      "BGName": 0,
      "BGEffect": 1377724294,
      "PopupFileName": "",
      "ScriptKr": "5;히나타;06;……죄송해요. 폐를 끼치러 왔습니다.\n#5;greeting\n#5;a",
      "TextJp": "す、すみません、お邪魔します……。",
      "TextTh": "ขอโทษนะคะ ฉันมาที่นี่เพื่อรบกวนค่ะ",
      "TextTw": "不好意思打擾了……",
      "TextEn": "Apologies for barging in like this.",
      "VoiceId": 0,
      "TeenMode": false
    },
    {
      "GroupId": 32180,
      "SelectionGroup": 0,
      "BGMId": 0,
      "Sound": "",
      "Transition": 0,
      "BGName": 0,
      "BGEffect": 1377724294,
      "PopupFileName": "",
      "ScriptKr": "1;마리;09\n5;히나타;06\n3;사쿠라코;99;시스터후드. 지금까지의 관습을 깨고 티파티의 내분에 개입하겠습니다.\n#3;a",
      "TextJp": "シスターフッド、これまでの慣習に反することではありますが……ティーパーティーの内紛に、介入させていただきます。",
      "TextTh": "ชมรมซิสเตอร์จะขอไม่รักษาธรรมเนียมที่มีอยู่ และเข้ามาแทรกแซงการทะเลาะกันภายในของสภาน้ำชาค่ะ",
      "TextTw": "修女會決定打破以往的慣例……在此介入茶會的內部紛爭。",
      "TextEn": "We've decided to break our customs and involve ourselves with the Tea Party's internal struggle.",
      "VoiceId": 0,
      "TeenMode": false
    },
    {
      "GroupId": 32180,
      "SelectionGroup": 0,
      "BGMId": 0,
      "Sound": "",
      "Transition": 0,
      "BGName": 0,
      "BGEffect": 1377724294,
      "PopupFileName": "",
      "ScriptKr": "1;마리;01\n5;히나타;01\n3;사쿠라코;01;티파티 미소노 미카 씨. 다른 티파티 멤버의 상해 교사 및 상해 미수로 시스터후드의 자율규제에 들어가겠습니다.\n#3;em;[반응]\n#1;h\n#5;h\n#3;h",
      "TextJp": "ティーパーティーの[ruby=みその]聖園[/ruby]ミカさん。他のティーパーティーメンバーへの傷害教唆及び傷害未遂で、あなたの身柄を確保します。",
      "TextTh": "คุณมิโซโนะ มิกะ จากสภาน้ำชา คุณจะต้องเข้ารับการควบคุมตนเองในความผิดยุยง#nและพยายามทำร้ายร่างกายสมาชิกสภาน้ำชาค่ะ",
      "TextTw": "茶會的聖園彌香同學──#n我以對其他茶會成員的教唆傷害，以及傷害未遂的罪名逮捕你。",
      "TextEn": "Misono Mika of the Tea Party. You are under arrest for attempting and instigating harm to your fellow Tea Party members.",
      "VoiceId": 0,
      "TeenMode": false
    },
    {
      "GroupId": 32180,
      "SelectionGroup": 0,
      "BGMId": 0,
      "Sound": "",
      "Transition": 348351892,
      "BGName": 1047754314,
      "BGEffect": 0,
      "PopupFileName": "",
      "ScriptKr": "#all;hide",
      "TextJp": "",
      "TextTh": "",
      "TextTw": "",
      "TextEn": "",
      "VoiceId": 0,
      "TeenMode": false
    },
    {
      "GroupId": 32180,
      "SelectionGroup": 0,
      "BGMId": 0,
      "Sound": "",
      "Transition": 2136104277,
      "BGName": 3932013926,
      "BGEffect": 0,
      "PopupFileName": "",
      "ScriptKr": "1;하나코;05\n5;미카;09\n#1;h\n#5;h",
      "TextJp": "",
      "TextTh": "",
      "TextTw": "",
      "TextEn": "",
      "VoiceId": 0,
      "TeenMode": false
    },
    {
      "GroupId": 32180,
      "SelectionGroup": 0,
      "BGMId": 0,
      "Sound": "",
      "Transition": 0,
      "BGName": 0,
      "BGEffect": 0,
      "PopupFileName": "",
      "ScriptKr": "5;미카;09;어라…… 그러니까, 시스터후드의 사쿠라코 쨩이지?",
      "TextJp": "シスターフッド、[ruby=うたずみ]歌住[/ruby]サクラコ……。",
      "TextTh": "เอ๋... เธอคือซากุระโกะจังจากชมรมซิสเตอร์สินะ?",
      "TextTw": "咦……是修女會的歌住櫻子啊？",
      "TextEn": "You must be Utazumi Sakurako of the Sisterhood.",
      "VoiceId": 0,
      "TeenMode": false
    },
    {
      "GroupId": 32180,
      "SelectionGroup": 0,
      "BGMId": 0,
      "Sound": "",
      "Transition": 0,
      "BGName": 0,
      "BGEffect": 0,
      "PopupFileName": "",
      "ScriptKr": "5;미카;10;아하하. 시스터후드랑은 처음 싸워보네. 응. 이게 너희가 준비한 비장의 카드야? \n#5;em;[재잘]\n#5;hophop",
      "TextJp": "……あはっ。流石にシスターフッドと戦うのは初めてだなー。なるほどね、これが切り札ってこと？",
      "TextTh": "อะฮ่ะฮ่า เป็นครั้งแรกเลยนะเนี่ยที่ได้สู้กับชมรมซิสเตอร์ นี่คือไพ่ลับที่พวกเธอเตรียมเอาไว้งั้นเหรอ?",
      "TextTw": "啊哈哈，跟修女會的戰鬥還是第一次呢。#n原來如此，這就是你們的王牌嗎？",
      "TextEn": "Hahaha! This is my first time fighting the Sisterhood! So is this the trump card you've had up your sleeve? ",
      "VoiceId": 0,
      "TeenMode": false
    },
    {
      "GroupId": 32180,
      "SelectionGroup": 0,
      "BGMId": 0,
      "Sound": "",
      "Transition": 0,
      "BGName": 0,
      "BGEffect": 0,
      "PopupFileName": "",
      "ScriptKr": "5;미카;15;대체 어떻게 시스터후드를 움직이게 만든 거야? 하나코 쨩?",
      "TextJp": "……浦和ハナコ、どうやってシスターフッドを動かしたの？",
      "TextTh": "ฮานาโกะจัง เธอทำยังไงถึงทำให้ชมรมซิสเตอร์ออกมาเคลื่อนไหวแบบนี้ได้ล่ะ?",
      "TextTw": "你是怎麼讓修女會行動的呢，花子醬？",
      "TextEn": "Just how did you manage to get them involved, Hanako?",
      "VoiceId": 0,
      "TeenMode": false
    },
    {
      "GroupId": 32180,
      "SelectionGroup": 0,
      "BGMId": 0,
      "Sound": "",
      "Transition": 0,
      "BGName": 0,
      "BGEffect": 0,
      "PopupFileName": "",
      "ScriptKr": "5;미카;02;너는 시스터후드들과 친했었지? 대체 뭘 대가로 지불한 거야? 저 수상쩍은 녀석들이 아무 이득없이 움직일 리가 없는데 말야.",
      "TextJp": "シスターたちと仲良かったのは知ってる。でもあの子たちが何の得も無く動くはずが無い……ねえ、[ruby=・   ・   ・   ・   ・   ・]何を支払った[/ruby]の？",
      "TextTh": "เธอเคยสนิทกับพวกซิสเตอร์ใช่ไหม? เธอยอมจ่ายด้วยอะไรเพื่อแลกมาล่ะ? ไม่มีทางที่พวกที่มีพิรุธจะเคลื่อนไหวได้โดยไม่ได้รับอะไรเป็นการตอบแทนหรอก ว่าไหมล่ะ?",
      "TextTw": "你之前跟修女們的感情似乎很不錯吧？#n那些可疑的傢伙不太可能毫無理由地行動……你究竟付出了什麼代價？",
      "TextEn": "I knew you were acquainted with them at one point, just as you were with everyone. What did you offer in return, I wonder. These interlopers wouldn't lift a finger unless they stood to gain something from it.",
      "VoiceId": 0,
      "TeenMode": false
    },
    {
      "GroupId": 32180,
      "SelectionGroup": 0,
      "BGMId": 0,
      "Sound": "",
      "Transition": 0,
      "BGName": 0,
      "BGEffect": 0,
      "PopupFileName": "",
      "ScriptKr": "1;하나코;05;…….",
      "TextJp": "……。",
      "TextTh": ".......",
      "TextTw": "……",
      "TextEn": "...",
      "VoiceId": 0,
      "TeenMode": false
    },
    {
      "GroupId": 32180,
      "SelectionGroup": 0,
      "BGMId": 0,
      "Sound": "",
      "Transition": 0,
      "BGName": 0,
      "BGEffect": 0,
      "PopupFileName": "",
      "ScriptKr": "5;미카;99;……재미있겠네. 해치워야 할 사람들이 더 늘어나는 건 귀찮지만.",
      "TextJp": "……うん、興味深いね。さて、片付けないといけない相手が一気に増えちゃったなぁ。",
      "TextTh": "มันน่ารำคาญนะที่ต้องมีคนให้จัดการเพิ่มขึ้น... แต่ยังไงก็คงจะสนุกดี",
      "TextTw": "……真讓人好奇呢。#n雖然必須收拾的對象增加是有點麻煩。",
      "TextEn": "How intriguing, though I do find it annoying to have more pests to exterminate.",
      "VoiceId": 0,
      "TeenMode": false
    },
    {
      "GroupId": 32180,
      "SelectionGroup": 0,
      "BGMId": 0,
      "Sound": "",
      "Transition": 0,
      "BGName": 0,
      "BGEffect": 0,
      "PopupFileName": "",
      "ScriptKr": "1;하나코;06;……. 동요하고 있군요, 미카 씨.",
      "TextJp": "……ようやく顔色が変わりましたね、ミカさん？",
      "TextTh": "คุณมิกะ คุณกำลังกระสับกระส่ายสินะคะ...",
      "TextTw": "……臉色終於變了呢，彌香同學。",
      "TextEn": "Sounds to me like you're becoming restless, Mika.",
      "VoiceId": 0,
      "TeenMode": false
    },
    {
      "GroupId": 32180,
      "SelectionGroup": 0,
      "BGMId": 0,
      "Sound": "",
      "Transition": 0,
      "BGName": 0,
      "BGEffect": 0,
      "PopupFileName": "",
      "ScriptKr": "5;미카;01;아니, 어차피 호스트가 되면 대성당도 청소하려고 했으니까, 응. 귀찮은 일을 한꺼번에 한다고 생각하지 뭐.",
      "TextJp": "……そうかな？まあどうせホストになったら、大聖堂も掃除しようと思ってたところだし。うん、一気にやれるチャンスだって考えることにしようかな。",
      "TextTh": "ก็เปล่านี่ ถ้าอยากขึ้นเป็นโฮสต์ ยังไงฉันก็ต้องจัดการมหาวิหารอยู่แล้ว#nอืม... ก็คิดซะว่าต้องทำเรื่องที่น่ารำคาญพร้อมๆ กันเลยแล้วกัน",
      "TextTw": "是嗎？我本來就打算在當上主席後清掃一下大教堂。#n嗯，就當作是把麻煩的事情一起解決吧。",
      "TextEn": "I planned to clean out the cathedral when I became host anyway. This just saves me some time.",
      "VoiceId": 0,
      "TeenMode": false
    },
    {
      "GroupId": 32180,
      "SelectionGroup": 0,
      "BGMId": 0,
      "Sound": "",
      "Transition": 0,
      "BGName": 0,
      "BGEffect": 0,
      "PopupFileName": "",
      "ScriptKr": "#st;[0,0];instant;1;",
      "TextJp": "",
      "TextTh": "",
      "TextTw": "",
      "TextEn": "",
      "VoiceId": 0,
      "TeenMode": false
    },
    {
      "GroupId": 32180,
      "SelectionGroup": 0,
      "BGMId": 0,
      "Sound": "",
      "Transition": 0,
      "BGName": 0,
      "BGEffect": 0,
      "PopupFileName": "",
      "ScriptKr": "#clearST",
      "TextJp": "",
      "TextTh": "",
      "TextTw": "",
      "TextEn": "",
      "VoiceId": 0,
      "TeenMode": false
    },
    {
      "GroupId": 32180,
      "SelectionGroup": 0,
      "BGMId": 0,
      "Sound": "",
      "Transition": 0,
      "BGName": 0,
      "BGEffect": 0,
      "PopupFileName": "",
      "ScriptKr": "5;미카;01\n#5;m3\n#1;dl\n#wait;1000",
      "TextJp": "",
      "TextTh": "",
      "TextTw": "",
      "TextEn": "",
      "VoiceId": 0,
      "TeenMode": false
    },
    {
      "GroupId": 32180,
      "SelectionGroup": 0,
      "BGMId": 0,
      "Sound": "",
      "Transition": 0,
      "BGName": 0,
      "BGEffect": 0,
      "PopupFileName": "",
      "ScriptKr": "#all;hide",
      "TextJp": "",
      "TextTh": "",
      "TextTw": "",
      "TextEn": "",
      "VoiceId": 0,
      "TeenMode": false
    },
    {
      "GroupId": 32180,
      "SelectionGroup": 0,
      "BGMId": 0,
      "Sound": "",
      "Transition": 0,
      "BGName": 0,
      "BGEffect": 0,
      "PopupFileName": "",
      "ScriptKr": "3;미카;03;좋아. 그럼 다시 해볼까?\n#3;em;[반짝]",
      "TextJp": "……さて、じゃあやってみよっか？",
      "TextTh": "เอาล่ะ มางั้นลองดูอีกสักตั้ง",
      "TextTw": "……那麼就繼續戰鬥吧？",
      "TextEn": "All right, everyone. Shall we get started?",
      "VoiceId": 0,
      "TeenMode": false
    },
    {
      "GroupId": 32180,
      "SelectionGroup": 0,
      "BGMId": 0,
      "Sound": "",
      "Transition": 0,
      "BGName": 0,
      "BGEffect": 0,
      "PopupFileName": "",
      "ScriptKr": "#st;[0,0];instant;1;",
      "TextJp": "",
      "TextTh": "",
      "TextTw": "",
      "TextEn": "",
      "VoiceId": 0,
      "TeenMode": false
    },
    {
      "GroupId": 32180,
      "SelectionGroup": 0,
      "BGMId": 0,
      "Sound": "",
      "Transition": 0,
      "BGName": 0,
      "BGEffect": 0,
      "PopupFileName": "",
      "ScriptKr": "#clearST",
      "TextJp": "",
      "TextTh": "",
      "TextTw": "",
      "TextEn": "",
      "VoiceId": 0,
      "TeenMode": false
    },
    {
      "GroupId": 32180,
      "SelectionGroup": 0,
      "BGMId": 0,
      "Sound": "SE_Reload_02",
      "Transition": 0,
      "BGName": 0,
      "BGEffect": 0,
      "PopupFileName": "",
      "ScriptKr": "3;미카;01\n#3;greeting\n#wait;1500\n#3;closeup",
      "TextJp": "",
      "TextTh": "",
      "TextTw": "",
      "TextEn": "",
      "VoiceId": 0,
      "TeenMode": false
    },
    {
      "GroupId": 32180,
      "SelectionGroup": 0,
      "BGMId": 0,
      "Sound": "",
      "Transition": 0,
      "BGName": 0,
      "BGEffect": 0,
      "PopupFileName": "",
      "ScriptKr": "3;하나코;06;미카 씨! 더 싸울 생각인가요? 당신에게 승산은 없습니다. 총을 버리세요!\n#3;em;[반응]\n#3;closeup",
      "TextJp": "……あくまでも戦うつもりですか、ミカさん。この状況での勝算がどれくらいか、分からないあなたではないですよね？",
      "TextTh": "คุณมิกะ! ยังคิดจะสู้ต่อเหรอคะ? คุณไม่มีทางชนะหรอก วางปืนเถอะค่ะ!",
      "TextTw": "彌香同學！你還想繼續戰鬥嗎？#n你已經沒有勝算了，乖乖放下武器投降吧！",
      "TextEn": "Do you really intend to keep fighting?! It's pointless, Mika. Put down your weapon.",
      "VoiceId": 0,
      "TeenMode": false
    },
    {
      "GroupId": 32180,
      "SelectionGroup": 0,
      "BGMId": 0,
      "Sound": "",
      "Transition": 0,
      "BGName": 0,
      "BGEffect": 0,
      "PopupFileName": "",
      "ScriptKr": "3;미카;99;응, 그럴지도. 하지만 여기까지 와서 순순히 항복할 수는 없잖아? \n#3;closeup",
      "TextJp": "……うん、そうかもね。でもここまで来て、「おとなしく降参します」なんてわけにはいかないでしょ？",
      "TextTh": "อื้ม อาจจะไม่ชนะก็ได้ แต่มาถึงขนาดนี้แล้ว จะให้ยอมจำนนง่ายๆ ได้ยังไงล่ะ? ",
      "TextTw": "……嗯，或許是這樣沒錯。#n但是都走到這一步了，總不可能乖乖投降吧？",
      "TextEn": "That may be true, but I can't simply surrender. Not after coming this far.",
      "VoiceId": 0,
      "TeenMode": false
    },
    {
      "GroupId": 32180,
      "SelectionGroup": 0,
      "BGMId": 0,
      "Sound": "",
      "Transition": 1122508889,
      "BGName": 1047754314,
      "BGEffect": 0,
      "PopupFileName": "",
      "ScriptKr": "#all;hide",
      "TextJp": "",
      "TextTh": "",
      "TextTw": "",
      "TextEn": "",
      "VoiceId": 0,
      "TeenMode": false
    },
    {
      "GroupId": 32180,
      "SelectionGroup": 0,
      "BGMId": 0,
      "Sound": "",
      "Transition": 0,
      "BGName": 0,
      "BGEffect": 0,
      "PopupFileName": "",
      "ScriptKr": "#na;미카;갈 수 있는 데까지 가는 수밖에 없어.",
      "TextJp": "……もう私は、行くところまで行くしかないの。",
      "TextTh": "ฉันไม่มีทางเลือกอื่นนอกจากไปให้ถึงที่สุด",
      "TextTw": "我只能繼續前進了。",
      "TextEn": "I'll stop at nothing.",
      "VoiceId": 0,
      "TeenMode": false
    }
  ]
}